pion/__init__.py
pion/apion.py
pion/controller.py
pion/cython_pid.cpython-313-i386-linux-musl.so
pion/cython_pid.pyx
pion/gpion.py
pion/pio.py
pion/pion.py
pion/simulator.py
pion/spion.py
pion/trajectory.py
pion/scripts/__init__.py
pion/scripts/datac.py
pionfunc/__init__.py
pionfunc/annotation.py
pionfunc/functions.py
swarm_server/__init__.py
swarm_server/commands.py
swarm_server/datagram.proto
swarm_server/datagram.py
swarm_server/datagram_pb2.py
swarm_server/server.py
swarm_server/swarmsim.py
swarm_server/udpmulticast.py
swarm_server/scripts/params.py
swarm_server/scripts/server_radxa.py
swarm_server/scripts/server_raspberry.py
swarm_server/scripts/server_sim.py
swarm_server/scripts/server_uni.py
pionsdk-0.0.12.dist-info/METADATA
pionsdk-0.0.12.dist-info/WHEEL
pionsdk-0.0.12.dist-info/entry_points.txt
pionsdk-0.0.12.dist-info/top_level.txt
pionsdk-0.0.12.dist-info/RECORD
pionsdk-0.0.12.dist-info/licenses/LICENSE
