Metadata-Version: 2.4
Name: pionsdk
Version: 0.0.12
Summary: This module is needed to control drones
Author-email: Michael <onisoris@yandex.ru>
Maintainer-email: Michael <onisoris@yandex.ru>
License-Expression: MIT
Project-URL: Homepage, https://github.com/OnisOris/pion
Project-URL: Documentation, https://onisoris.github.io/pion
Project-URL: Repository, https://github.com/OnisOris/pion.git
Project-URL: Issues, https://github.com/OnisOris/pion/issues
Classifier: Development Status :: 3 - Alpha
Classifier: Intended Audience :: Developers
Classifier: Topic :: Software Development :: Build Tools
Classifier: Programming Language :: Python :: 3.10
Classifier: Programming Language :: Python :: 3.11
Classifier: Programming Language :: Python :: 3.12
Classifier: Programming Language :: Python :: 3.13
Requires-Python: >=3.10
License-File: LICENSE
Requires-Dist: numpy>=2.1.0
Requires-Dist: paramiko>=3.5.1
Requires-Dist: protobuf==5.29.3
Requires-Dist: pymavlink>=2.4.42
Requires-Dist: pyserial>=3.5
Requires-Dist: rich>=13.9.4
Requires-Dist: lokky>=0.0.8
Requires-Dist: python-dotenv>=1.1.0
Provides-Extra: plotting
Requires-Dist: matplotlib>=3.10.1; extra == "plotting"
Requires-Dist: tornado; extra == "plotting"
Dynamic: license-file
